sendroid/accelerometer.py
sendroid/audio.py
sendroid/barometer.py
sendroid/battery.py
sendroid/bluetooth.py
sendroid/brightness.py
sendroid/call.py
sendroid/camera.py
sendroid/compass.py
sendroid/cpu.py
sendroid/devicename.py
sendroid/email.py
sendroid/filechooser.py
sendroid/flash.py
sendroid/gps.py
sendroid/gravity.py
sendroid/gyroscope.py
sendroid/humidity.py
sendroid/irblaster.py
sendroid/keystore.py
sendroid/light.py
sendroid/notification.py
sendroid/orientation.py
sendroid/processors.py
sendroid/proximity.py
sendroid/screenshot.py
sendroid/sensor.py
sendroid/sms.py
sendroid/spatialorientation.py
sendroid/storagepath.py
sendroid/stt.py
sendroid/temperature.py
sendroid/tts.py
sendroid/uniqueid.py
sendroid/vibrator.py
sendroid/wifi.py
sendroid-1.0a6.dist-info/METADATA
sendroid-1.0a6.dist-info/WHEEL
sendroid-1.0a6.dist-info/licenses/LICENSE
sendroid-1.0a6.dist-info/RECORD
