Metadata-Version: 2.1
Name: sendroid
Version: 1.0a6
Summary: Simple android sensors manager
Project-URL: Homepage, https://github.com/bwilk315/sendroid
Author-email: bwilk315 <bwilk315@onet.pl>
License: 
License-File: LICENSE
Classifier: License :: OSI Approved :: GNU General Public License v2 (GPLv2)
Classifier: Operating System :: OS Independent
Classifier: Programming Language :: Python :: 3
Requires-Python: >=3.5
